promplate/__init__.py
promplate/chain/__init__.py
promplate/chain/callback.py
promplate/chain/node.py
promplate/chain/utils.py
promplate/llm/__init__.py
promplate/llm/base.py
promplate/llm/openai/__init__.py
promplate/llm/openai/v0.py
promplate/llm/openai/v1.py
promplate/prompt/__init__.py
promplate/prompt/builder.py
promplate/prompt/chat.py
promplate/prompt/template.py
promplate/prompt/utils.py
promplate-0.3.5.6.dist-info/METADATA
promplate-0.3.5.6.dist-info/WHEEL
promplate-0.3.5.6.dist-info/RECORD
