Metadata-Version: 2.4
Name: promplate
Version: 0.3.5.6
Summary: Prompt engineering framework for humans
License: MIT
Keywords: prompt,template,nlp,llm
Author: Muspi Merol
Author-email: me@promplate.dev
Requires-Python: >=3.10,<4.0
Classifier: Development Status :: 5 - Production/Stable
Classifier: License :: OSI Approved :: MIT License
Classifier: Programming Language :: Python :: 3
Classifier: Programming Language :: Python :: 3.10
Classifier: Programming Language :: Python :: 3.11
Classifier: Programming Language :: Python :: 3.12
Classifier: Programming Language :: Python :: 3.13
Classifier: Programming Language :: Python :: 3.14
Classifier: Topic :: Scientific/Engineering :: Artificial Intelligence
Classifier: Topic :: Text Processing :: Markup
Classifier: Typing :: Typed
Provides-Extra: aiofiles
Provides-Extra: all
Provides-Extra: httpx
Provides-Extra: openai
Requires-Dist: aiofiles (>=23.2) ; extra == "aiofiles" or extra == "all"
Requires-Dist: httpx (>=0.24,<1.0) ; extra == "httpx" or extra == "all"
Requires-Dist: openai (>=0.27,<3.0) ; extra == "openai" or extra == "all"
Requires-Dist: typing-extensions (>=4,<5) ; python_version < "3.12"
Project-URL: Documentation, https://docs.py.promplate.dev/
Project-URL: Homepage, https://promplate.dev/
Project-URL: Repository, https://github.com/promplate/core
